flow/__init__.py
flow/__main__.py
flow/aggregates.py
flow/directives.py
flow/environment.py
flow/errors.py
flow/labels.py
flow/project.py
flow/render_status.py
flow/template.py
flow/version.py
flow/environments/__init__.py
flow/environments/drexel.py
flow/environments/incite.py
flow/environments/purdue.py
flow/environments/umich.py
flow/environments/umn.py
flow/environments/xsede.py
flow/hooks/__init__.py
flow/hooks/git_util.py
flow/hooks/hooks.py
flow/hooks/track_operations.py
flow/hooks/util.py
flow/scheduling/__init__.py
flow/scheduling/base.py
flow/scheduling/fake_scheduler.py
flow/scheduling/lsf.py
flow/scheduling/pbs.py
flow/scheduling/simple_scheduler.py
flow/scheduling/slurm.py
flow/scripts/__init__.py
flow/scripts/template_test.py
flow/templates/__init__.py
flow/templates/andes.sh
flow/templates/anvil.sh
flow/templates/base_script.sh
flow/templates/base_status.jinja
flow/templates/base_status_compact.jinja
flow/templates/base_status_expand.jinja
flow/templates/base_status_stack.jinja
flow/templates/bridges2.sh
flow/templates/crusher.sh
flow/templates/custom_script_template.sh
flow/templates/delta.sh
flow/templates/drexel-picotte.sh
flow/templates/expanse.sh
flow/templates/frontier.sh
flow/templates/init_test_environment.pyt
flow/templates/lsf.sh
flow/templates/pbs.sh
flow/templates/project_example.pyt
flow/templates/project_minimal.pyt
flow/templates/project_test_environment.pyt
flow/templates/project_testing.pyt
flow/templates/script.sh
flow/templates/simple_scheduler.sh
flow/templates/slurm.sh
flow/templates/status.jinja
flow/templates/status_compact.jinja
flow/templates/status_expand.jinja
flow/templates/status_stack.jinja
flow/templates/summit.sh
flow/templates/umich-greatlakes.sh
flow/util/__init__.py
flow/util/config.py
flow/util/misc.py
flow/util/template_filters.py
flow/util/translate.py
flow/util/mistune/__init__.py
flow/util/mistune/block_parser.py
flow/util/mistune/inline_parser.py
flow/util/mistune/markdown.py
flow/util/mistune/renderers.py
signac_flow-0.29.0.dist-info/LICENSE.txt
signac_flow-0.29.0.dist-info/METADATA
signac_flow-0.29.0.dist-info/WHEEL
signac_flow-0.29.0.dist-info/entry_points.txt
signac_flow-0.29.0.dist-info/top_level.txt
signac_flow-0.29.0.dist-info/RECORD
