Metadata-Version: 2.1
Name: signac-flow
Version: 0.29.0
Summary: Simple workflow management for signac projects.
Author-email: "Carl Simon Adorf et al." <csadorf@umich.edu>
Maintainer-email: signac Developers <signac-support@umich.edu>
License: BSD 3-Clause License for the software signac-flow.
Project-URL: Homepage, https://signac.io
Project-URL: Documentation, https://docs.signac.io
Project-URL: Download, https://pypi.org/project/signac-flow/
Project-URL: Source, https://github.com/glotzerlab/signac-flow
Project-URL: Issues, https://github.com/glotzerlab/signac-flow/issues
Keywords: workflow management
Classifier: Development Status :: 4 - Beta
Classifier: Intended Audience :: Science/Research
Classifier: License :: OSI Approved :: BSD License
Classifier: Topic :: Scientific/Engineering :: Physics
Classifier: Programming Language :: Python :: 3.8
Classifier: Programming Language :: Python :: 3.9
Classifier: Programming Language :: Python :: 3.10
Classifier: Programming Language :: Python :: 3.11
Classifier: Programming Language :: Python :: 3.12
Classifier: Programming Language :: Python :: Implementation :: CPython
Requires-Python: >=3.8
License-File: LICENSE.txt
Requires-Dist: signac >=2.2.0
Requires-Dist: jinja2 >=3.0.0
Requires-Dist: cloudpickle >=1.6.0
Requires-Dist: deprecation >=2.0.0
Requires-Dist: tqdm >=4.60.0
Requires-Dist: jsonschema >=4.5.0
